AUTHORS
ChangeLog
LICENSE
MANIFEST.in
README.md
minimal-requirements.txt
pip.conf
requirements.txt
setup.cfg
setup.py
test-requirements.txt
pyp_sandbox.egg-info/PKG-INFO
pyp_sandbox.egg-info/SOURCES.txt
pyp_sandbox.egg-info/dependency_links.txt
pyp_sandbox.egg-info/entry_points.txt
pyp_sandbox.egg-info/not-zip-safe
pyp_sandbox.egg-info/requires.txt
pyp_sandbox.egg-info/top_level.txt
pypsandbox/__init__.py
pypsandbox/pypsandbox.py
pypsandbox/shell.py