Metadata-Version: 1.1
Name: pyp-sandbox
Version: 7abc960
Summary: Test package for distutils/setuptools/pbr experimentation.
Home-page: https://github.com/smlstvnh/pyp-sandbox
Author: samstav
Author-email: smlstvnh@gmail.com
License: UNKNOWN
Platform: UNKNOWN
Classifier: Programming Language :: Python
